{
    "data":[
        {
            "型号":"型号1",
            "飞行距离":"1000km",
            "飞行高度":"1000km",
            "飞行时间":"1hour",
            "载人数":"2",
            "制造国家":"cn",
            "价格":"$100000000",
            "使用年限":"5",
            "飞行最大速度":"500km/h",
            "承载最大数量":"100kg"
        },
        {
            "型号":"型号2",
            "飞行距离":"2000km",
            "飞行高度":"3000km",
            "飞行时间":"1hour",
            "载人数":"2",
            "制造国家":"cn",
            "价格":"$100300000",
            "使用年限":"5",
            "飞行最大速度":"520km/h",
            "承载最大数量":"100kg"
        },
        {
            "型号":"型号3",
            "飞行距离":"3000km",
            "飞行高度":"1000km",
            "飞行时间":"1hour",
            "载人数":"2",
            "制造国家":"cn",
            "价格":"$10003000",
            "使用年限":"5",
            "飞行最大速度":"500km/h",
            "承载最大数量":"100kg"
        },
        {
            "型号":"型号4",
            "飞行距离":"4000km",
            "飞行高度":"1000km",
            "飞行时间":"1hour",
            "载人数":"2",
            "制造国家":"cn",
            "价格":"$100000400",
            "使用年限":"5",
            "飞行最大速度":"500km/h",
            "承载最大数量":"100kg"
        }
    ]
}